bsyncpy/__init__.py
bsyncpy/bsync.py
bsyncpy/bsyncpy_generator.py
bsyncpy/bsyncpy_header.py
bsyncpy-0.3.0.dist-info/WHEEL
bsyncpy-0.3.0.dist-info/METADATA
bsyncpy-0.3.0.dist-info/RECORD
