Metadata-Version: 2.1
Name: bsyncpy
Version: 0.3.0
Summary: Tools to autogenerate a Python SDK for BuildingSync given an XSD
Author: Joel Bender
Author-email: joel@carrickbender.com
Requires-Python: >=3.7.9,<4.0.0
Classifier: Programming Language :: Python :: 3
Classifier: Programming Language :: Python :: 3.8
Classifier: Programming Language :: Python :: 3.9
Classifier: Programming Language :: Python :: 3.10
Classifier: Programming Language :: Python :: 3.11
Requires-Dist: lxml (>=4.6.3,<5.0.0)
